git_batch_commit/__init__.py
git_batch_commit/__main__.py
git_batch_commit/cli.py
git_batch_commit/main.py
git_batch_commit-1.0.5.dist-info/METADATA
git_batch_commit-1.0.5.dist-info/WHEEL
git_batch_commit-1.0.5.dist-info/entry_points.txt
git_batch_commit-1.0.5.dist-info/top_level.txt
git_batch_commit-1.0.5.dist-info/RECORD
