Metadata-Version: 2.1
Name: git-batch-commit
Version: 1.0.5
Summary: A powerful Git batch commit tool that stages, commits, and pushes files in customizable batches.
Author: Vaishal
Project-URL: GitHub, https://github.com/Vaishal-Business/git-batch-commit
Classifier: Programming Language :: Python :: 3
Classifier: License :: OSI Approved :: MIT License
Classifier: Operating System :: OS Independent
Classifier: Topic :: Software Development :: Version Control :: Git
Requires-Python: >=3.6
Requires-Dist: gitpython
Requires-Dist: rich
